[{"location": "Харківська", "target": "Air bomb", "direction": "Пуски керованих авіаційних бомб тактичною авіацією у напрямку Харкова та прикордоння"}, {"location": "Одеська", "target": "Drone", "direction": "Розвідувальний БпЛА в акваторії Чорного моря в бік Білгород-Дністровського району"}, {"location": "Сумська", "target": "Aviation", "direction": "Активність ворожої тактичної авіації на північно-східному кордоні, загроза авіаційних засобів ураження"}, {"location": "Херсонська", "target": "Drone", "direction": "Ударні БпЛА типу Shahed з боку ТОТ Криму в напрямку Бериславського району"}]